django_hexagonal_cli/__init__.py
django_hexagonal_cli/cli.py
django_hexagonal_cli/templates/app/__init__.py-tpl
django_hexagonal_cli/templates/app/admin.py-tpl
django_hexagonal_cli/templates/app/application/__init__.py-tpl
django_hexagonal_cli/templates/app/apps.py-tpl
django_hexagonal_cli/templates/app/domain/__init__.py-tpl
django_hexagonal_cli/templates/app/infrastructure/__init__.py-tpl
django_hexagonal_cli/templates/app/infrastructure/orm/__init__.py-tpl
django_hexagonal_cli/templates/app/infrastructure/orm/migrations/__init__.py-tpl
django_hexagonal_cli/templates/app/infrastructure/orm/models.py-tpl
django_hexagonal_cli/templates/app/interfaces/__init__.py-tpl
django_hexagonal_cli/templates/app/interfaces/urls.py-tpl
django_hexagonal_cli/templates/app/interfaces/views.py-tpl
django_hexagonal_cli/templates/project/README.md-tpl
django_hexagonal_cli/templates/project/pyproject.toml-tpl
django_hexagonal_cli/templates/project/src/apps/__init__.py-tpl
django_hexagonal_cli/templates/project/src/config/__init__.py-tpl
django_hexagonal_cli/templates/project/src/config/asgi.py-tpl
django_hexagonal_cli/templates/project/src/config/settings.py-tpl
django_hexagonal_cli/templates/project/src/config/urls.py-tpl
django_hexagonal_cli/templates/project/src/config/wsgi.py-tpl
django_hexagonal_cli/templates/project/src/manage.py-tpl
django_hexagonal_cli-0.1.1.dist-info/LICENSE
django_hexagonal_cli-0.1.1.dist-info/METADATA
django_hexagonal_cli-0.1.1.dist-info/WHEEL
django_hexagonal_cli-0.1.1.dist-info/entry_points.txt
django_hexagonal_cli-0.1.1.dist-info/RECORD
