Metadata-Version: 2.3
Name: django-hexagonal-cli
Version: 0.1.1
Summary: A command-line tool to generate Django projects and apps following the hexagonal (ports and adapters) architecture.
License: MIT
Keywords: django,hexagonal,cli,codegen
Author: brunogonzalezlla
Author-email: brunogllaga@icloud.com
Requires-Python: >=3.12,<4.0
Classifier: License :: OSI Approved :: MIT License
Classifier: Programming Language :: Python :: 3
Classifier: Programming Language :: Python :: 3.12
Classifier: Programming Language :: Python :: 3.13
